README.txt
setup.py
scmutils/ThreadPool.py
scmutils/__init__.py
scmutils/check_mw_md5.py
scmutils/checkcopiedbranchfpga.py
scmutils/knife_slave_server_disk.py
scmutils/sync_to_cfg.py
scmutils.egg-info/PKG-INFO
scmutils.egg-info/SOURCES.txt
scmutils.egg-info/dependency_links.txt
scmutils.egg-info/top_level.txt
scmutils.egg-info/zip-safe