Metadata-Version: 1.1
Name: scmutils
Version: 1.0.0
Summary: this is a test package for packing python liberaries tutorial.
Home-page: https://intranet.nokia.com/sites/global/pages/home.aspx
Author: xp
Author-email: xuping.xu@nokia.com
License: MIT
Keywords: test python package
Platform: UNKNOWN
Classifier: License :: OSI Approved :: MIT License
Classifier: Programming Language :: Python
Classifier: Intended Audience :: Developers
Classifier: Operating System :: OS Independent
